score_card_model/ScoreCardModel.py
score_card_model/__init__.py
score_card_model/utils.py
score_card_model-1.6.9.dist-info/METADATA
score_card_model-1.6.9.dist-info/WHEEL
score_card_model-1.6.9.dist-info/top_level.txt
score_card_model-1.6.9.dist-info/RECORD
