Metadata-Version: 2.1
Name: score-card-model
Version: 1.6.9
Summary: Risk Score Card Model
Home-page: https://github.com/skykiseki/score_card_model
Author: Wei, Zhihui
Author-email: evelinesdd@qq.com
License: MIT
Keywords: Risk Score Card
Platform: UNKNOWN
Classifier: Intended Audience :: Developers
Classifier: License :: OSI Approved :: MIT License
Classifier: Operating System :: OS Independent
Classifier: Natural Language :: Chinese (Simplified)
Classifier: Natural Language :: Chinese (Traditional)
Classifier: Programming Language :: Python
Classifier: Programming Language :: Python :: 3
Classifier: Programming Language :: Python :: 3.6
Classifier: Programming Language :: Python :: 3.7
Classifier: Topic :: Text Processing
Classifier: Topic :: Text Processing :: Indexing
Classifier: Topic :: Text Processing :: Linguistic
Requires-Python: >=3.6
Requires-Dist: pandas
Requires-Dist: numpy
Requires-Dist: dill (>=0.2.9)
Requires-Dist: seaborn (>=0.11.1)
Requires-Dist: scikit-learn
Requires-Dist: statsmodels (>=0.12.2)
Requires-Dist: matplotlib
Requires-Dist: seaborn
Requires-Dist: tqdm
